base_model/MediaHandler.py
base_model/__init__.py
image_utils/__init__.py
image_utils/gpt_prompt.md
image_utils/converters/__init__.py
image_utils/converters/format_converter.py
image_utils/converters/image_to_text.py
image_utils/converters/text_add_to_image.py
image_utils/core/__init__.py
image_utils/core/exceptions.py
image_utils/core/image_handler.py
image_utils/editors/__init__.py
image_utils/editors/cropper.py
image_utils/editors/resizer.py
image_utils/tests/__init__.py
image_utils/tests/test_converters.py
image_utils/tests/test_editors.py
image_utils/tests/test_utils.py
image_utils/utils/__init__.py
image_utils/utils/image_utils.py
mp3_utils/__init__.py
mp3_utils/gpt_prompt.md
mp3_utils/converters/__init__.py
mp3_utils/converters/audio_format_converter.py
mp3_utils/converters/mp3_to_text.py
mp3_utils/core/__init__.py
mp3_utils/core/exceptions.py
mp3_utils/core/mp3_handler.py
mp3_utils/editors/__init__.py
mp3_utils/editors/effects.py
mp3_utils/editors/trimmer.py
mp3_utils/tests/__init__.py
mp3_utils/tests/test_converters.py
mp3_utils/tests/test_editors.py
mp3_utils/utils/__init__.py
mp3_utils/utils/mp3_utils.py
mp4_utils/__init__.py
mp4_utils/gpt_prompt.md
mp4_utils/converters/__init__.py
mp4_utils/converters/mp4_to_gif.py
mp4_utils/converters/mp4_to_mp3.py
mp4_utils/converters/mp4_to_pngs.py
mp4_utils/converters/tv_to_mp4.py
mp4_utils/core/__init__.py
mp4_utils/core/exceptions.py
mp4_utils/core/mp4_handler.py
mp4_utils/editors/__init__.py
mp4_utils/editors/orientation.py
mp4_utils/editors/resizer.py
mp4_utils/tests/__init__.py
mp4_utils/tests/test_converters.py
mp4_utils/tests/test_editors.py
mp4_utils/utils/__init__.py
mp4_utils/utils/file_utils.py
mp4_utils/utils/mp4_utils.py
tree_utils/__init__.py
tree_utils/struct_tree_out.py
easy_media_utils-0.1.5.dist-info/LICENSE
easy_media_utils-0.1.5.dist-info/METADATA
easy_media_utils-0.1.5.dist-info/WHEEL
easy_media_utils-0.1.5.dist-info/entry_points.txt
easy_media_utils-0.1.5.dist-info/top_level.txt
easy_media_utils-0.1.5.dist-info/RECORD
