Metadata-Version: 2.1
Name: easy-media-utils
Version: 0.1.5
Summary: A collection of Python utilities for handling media files.
Home-page: https://github.com/aceliuchanghong/easy-media-utils.git
Author: Sisconsavior
Author-email: aceliuchanghong@gmail.com
License: LICENSE
Keywords: media handling image audio video conversion editing
Classifier: Development Status :: 3 - Alpha
Classifier: Intended Audience :: Developers
Classifier: Topic :: Software Development :: Libraries :: Python Modules
Classifier: License :: OSI Approved :: MIT License
Classifier: Programming Language :: Python :: 3.11
Requires-Python: >=3.6
License-File: LICENSE
Requires-Dist: pillow ==10.2.0
